simuleval/__init__.py
simuleval/cli.py
simuleval/options.py
simuleval/agents/__init__.py
simuleval/agents/actions.py
simuleval/agents/agent.py
simuleval/agents/pipeline.py
simuleval/agents/service.py
simuleval/agents/states.py
simuleval/data/__init__.py
simuleval/data/segments.py
simuleval/data/dataloader/__init__.py
simuleval/data/dataloader/dataloader.py
simuleval/data/dataloader/s2t_dataloader.py
simuleval/data/dataloader/t2t_dataloader.py
simuleval/evaluator/__init__.py
simuleval/evaluator/evaluator.py
simuleval/evaluator/instance.py
simuleval/evaluator/remote.py
simuleval/evaluator/scorers/__init__.py
simuleval/evaluator/scorers/latency_scorer.py
simuleval/evaluator/scorers/quality_scorer.py
simuleval/utils/__init__.py
simuleval/utils/agent.py
simuleval/utils/arguments.py
simuleval/utils/functional.py
simuleval/utils/slurm.py
simuleval-1.1.4.dist-info/LICENSE
simuleval-1.1.4.dist-info/METADATA
simuleval-1.1.4.dist-info/WHEEL
simuleval-1.1.4.dist-info/entry_points.txt
simuleval-1.1.4.dist-info/top_level.txt
simuleval-1.1.4.dist-info/RECORD
