Metadata-Version: 2.1
Name: simuleval
Version: 1.1.4
Summary: SimulEval: A Flexible Toolkit for Automated Machine Translation Evaluation
Author: Xutai Ma
License: LICENSE
Keywords: SimulEval,Machine Translation,Evaluation,Metrics,BLEU,TER,METEOR,chrF,RIBES,WMD,Embedding Average,Embedding Extrema,Embedding Greedy,Embedding Average,SimulEval,SimulEval_Testing_Package_1,facebookresearch,facebook,Meta-Evaluation
Classifier: Programming Language :: Python :: 3
Classifier: License :: OSI Approved :: Apache Software License
Classifier: Operating System :: OS Independent
Classifier: Development Status :: 4 - Beta
Requires-Python: >3.7.0
License-File: LICENSE
Requires-Dist: pytest
Requires-Dist: pytest-cov
Requires-Dist: sacrebleu >=2.3.1
Requires-Dist: tornado
Requires-Dist: soundfile
Requires-Dist: pandas
Requires-Dist: requests
Requires-Dist: pytest-flake8
Requires-Dist: textgrid
Requires-Dist: tqdm ==4.64.1
Requires-Dist: pyyaml
Requires-Dist: bitarray ==2.6.0
Requires-Dist: yt-dlp
Requires-Dist: pydub
